{"nodes": [{"id": "c_apache24_htdocs_ai_vendor_laravel_breeze_stubs_inertia_common_tests_feature_profiletest_php", "label": "ProfileTest.php", "file_type": "code", "source_file": "C:\\Apache24\\htdocs\\ai\\vendor\\laravel\\breeze\\stubs\\inertia-common\\tests\\Feature\\ProfileTest.php", "source_location": "L1"}, {"id": "profiletest_profiletest", "label": "ProfileTest", "file_type": "code", "source_file": "C:\\Apache24\\htdocs\\ai\\vendor\\laravel\\breeze\\stubs\\inertia-common\\tests\\Feature\\ProfileTest.php", "source_location": "L9"}, {"id": "profiletest_profiletest_test_profile_page_is_displayed", "label": ".test_profile_page_is_displayed()", "file_type": "code", "source_file": "C:\\Apache24\\htdocs\\ai\\vendor\\laravel\\breeze\\stubs\\inertia-common\\tests\\Feature\\ProfileTest.php", "source_location": "L13"}, {"id": "profiletest_profiletest_test_profile_information_can_be_updated", "label": ".test_profile_information_can_be_updated()", "file_type": "code", "source_file": "C:\\Apache24\\htdocs\\ai\\vendor\\laravel\\breeze\\stubs\\inertia-common\\tests\\Feature\\ProfileTest.php", "source_location": "L24"}, {"id": "profiletest_profiletest_test_email_verification_status_is_unchanged_when_the_email_address_is_unchanged", "label": ".test_email_verification_status_is_unchanged_when_the_email_address_is_unchanged()", "file_type": "code", "source_file": "C:\\Apache24\\htdocs\\ai\\vendor\\laravel\\breeze\\stubs\\inertia-common\\tests\\Feature\\ProfileTest.php", "source_location": "L46"}, {"id": "profiletest_profiletest_test_user_can_delete_their_account", "label": ".test_user_can_delete_their_account()", "file_type": "code", "source_file": "C:\\Apache24\\htdocs\\ai\\vendor\\laravel\\breeze\\stubs\\inertia-common\\tests\\Feature\\ProfileTest.php", "source_location": "L64"}, {"id": "profiletest_profiletest_test_correct_password_must_be_provided_to_delete_account", "label": ".test_correct_password_must_be_provided_to_delete_account()", "file_type": "code", "source_file": "C:\\Apache24\\htdocs\\ai\\vendor\\laravel\\breeze\\stubs\\inertia-common\\tests\\Feature\\ProfileTest.php", "source_location": "L82"}], "edges": [{"source": "c_apache24_htdocs_ai_vendor_laravel_breeze_stubs_inertia_common_tests_feature_profiletest_php", "target": "user", "relation": "imports", "confidence": "EXTRACTED", "source_file": "C:\\Apache24\\htdocs\\ai\\vendor\\laravel\\breeze\\stubs\\inertia-common\\tests\\Feature\\ProfileTest.php", "source_location": "L5", "weight": 1.0}, {"source": "c_apache24_htdocs_ai_vendor_laravel_breeze_stubs_inertia_common_tests_feature_profiletest_php", "target": "refreshdatabase", "relation": "imports", "confidence": "EXTRACTED", "source_file": "C:\\Apache24\\htdocs\\ai\\vendor\\laravel\\breeze\\stubs\\inertia-common\\tests\\Feature\\ProfileTest.php", "source_location": "L6", "weight": 1.0}, {"source": "c_apache24_htdocs_ai_vendor_laravel_breeze_stubs_inertia_common_tests_feature_profiletest_php", "target": "testcase", "relation": "imports", "confidence": "EXTRACTED", "source_file": "C:\\Apache24\\htdocs\\ai\\vendor\\laravel\\breeze\\stubs\\inertia-common\\tests\\Feature\\ProfileTest.php", "source_location": "L7", "weight": 1.0}, {"source": "c_apache24_htdocs_ai_vendor_laravel_breeze_stubs_inertia_common_tests_feature_profiletest_php", "target": "profiletest_profiletest", "relation": "contains", "confidence": "EXTRACTED", "source_file": "C:\\Apache24\\htdocs\\ai\\vendor\\laravel\\breeze\\stubs\\inertia-common\\tests\\Feature\\ProfileTest.php", "source_location": "L9", "weight": 1.0}, {"source": "profiletest_profiletest", "target": "profiletest_profiletest_test_profile_page_is_displayed", "relation": "method", "confidence": "EXTRACTED", "source_file": "C:\\Apache24\\htdocs\\ai\\vendor\\laravel\\breeze\\stubs\\inertia-common\\tests\\Feature\\ProfileTest.php", "source_location": "L13", "weight": 1.0}, {"source": "profiletest_profiletest", "target": "profiletest_profiletest_test_profile_information_can_be_updated", "relation": "method", "confidence": "EXTRACTED", "source_file": "C:\\Apache24\\htdocs\\ai\\vendor\\laravel\\breeze\\stubs\\inertia-common\\tests\\Feature\\ProfileTest.php", "source_location": "L24", "weight": 1.0}, {"source": "profiletest_profiletest", "target": "profiletest_profiletest_test_email_verification_status_is_unchanged_when_the_email_address_is_unchanged", "relation": "method", "confidence": "EXTRACTED", "source_file": "C:\\Apache24\\htdocs\\ai\\vendor\\laravel\\breeze\\stubs\\inertia-common\\tests\\Feature\\ProfileTest.php", "source_location": "L46", "weight": 1.0}, {"source": "profiletest_profiletest", "target": "profiletest_profiletest_test_user_can_delete_their_account", "relation": "method", "confidence": "EXTRACTED", "source_file": "C:\\Apache24\\htdocs\\ai\\vendor\\laravel\\breeze\\stubs\\inertia-common\\tests\\Feature\\ProfileTest.php", "source_location": "L64", "weight": 1.0}, {"source": "profiletest_profiletest", "target": "profiletest_profiletest_test_correct_password_must_be_provided_to_delete_account", "relation": "method", "confidence": "EXTRACTED", "source_file": "C:\\Apache24\\htdocs\\ai\\vendor\\laravel\\breeze\\stubs\\inertia-common\\tests\\Feature\\ProfileTest.php", "source_location": "L82", "weight": 1.0}], "raw_calls": [{"caller_nid": "profiletest_profiletest_test_profile_page_is_displayed", "callee": "create", "source_file": "C:\\Apache24\\htdocs\\ai\\vendor\\laravel\\breeze\\stubs\\inertia-common\\tests\\Feature\\ProfileTest.php", "source_location": "L15"}, {"caller_nid": "profiletest_profiletest_test_profile_page_is_displayed", "callee": "User", "source_file": "C:\\Apache24\\htdocs\\ai\\vendor\\laravel\\breeze\\stubs\\inertia-common\\tests\\Feature\\ProfileTest.php", "source_location": "L15"}, {"caller_nid": "profiletest_profiletest_test_profile_page_is_displayed", "callee": "get", "source_file": "C:\\Apache24\\htdocs\\ai\\vendor\\laravel\\breeze\\stubs\\inertia-common\\tests\\Feature\\ProfileTest.php", "source_location": "L17"}, {"caller_nid": "profiletest_profiletest_test_profile_page_is_displayed", "callee": "actingAs", "source_file": "C:\\Apache24\\htdocs\\ai\\vendor\\laravel\\breeze\\stubs\\inertia-common\\tests\\Feature\\ProfileTest.php", "source_location": "L17"}, {"caller_nid": "profiletest_profiletest_test_profile_page_is_displayed", "callee": "assertOk", "source_file": "C:\\Apache24\\htdocs\\ai\\vendor\\laravel\\breeze\\stubs\\inertia-common\\tests\\Feature\\ProfileTest.php", "source_location": "L21"}, {"caller_nid": "profiletest_profiletest_test_profile_information_can_be_updated", "callee": "create", "source_file": "C:\\Apache24\\htdocs\\ai\\vendor\\laravel\\breeze\\stubs\\inertia-common\\tests\\Feature\\ProfileTest.php", "source_location": "L26"}, {"caller_nid": "profiletest_profiletest_test_profile_information_can_be_updated", "callee": "User", "source_file": "C:\\Apache24\\htdocs\\ai\\vendor\\laravel\\breeze\\stubs\\inertia-common\\tests\\Feature\\ProfileTest.php", "source_location": "L26"}, {"caller_nid": "profiletest_profiletest_test_profile_information_can_be_updated", "callee": "patch", "source_file": "C:\\Apache24\\htdocs\\ai\\vendor\\laravel\\breeze\\stubs\\inertia-common\\tests\\Feature\\ProfileTest.php", "source_location": "L28"}, {"caller_nid": "profiletest_profiletest_test_profile_information_can_be_updated", "callee": "actingAs", "source_file": "C:\\Apache24\\htdocs\\ai\\vendor\\laravel\\breeze\\stubs\\inertia-common\\tests\\Feature\\ProfileTest.php", "source_location": "L28"}, {"caller_nid": "profiletest_profiletest_test_profile_information_can_be_updated", "callee": "assertRedirect", "source_file": "C:\\Apache24\\htdocs\\ai\\vendor\\laravel\\breeze\\stubs\\inertia-common\\tests\\Feature\\ProfileTest.php", "source_location": "L35"}, {"caller_nid": "profiletest_profiletest_test_profile_information_can_be_updated", "callee": "assertSessionHasNoErrors", "source_file": "C:\\Apache24\\htdocs\\ai\\vendor\\laravel\\breeze\\stubs\\inertia-common\\tests\\Feature\\ProfileTest.php", "source_location": "L35"}, {"caller_nid": "profiletest_profiletest_test_profile_information_can_be_updated", "callee": "refresh", "source_file": "C:\\Apache24\\htdocs\\ai\\vendor\\laravel\\breeze\\stubs\\inertia-common\\tests\\Feature\\ProfileTest.php", "source_location": "L39"}, {"caller_nid": "profiletest_profiletest_test_profile_information_can_be_updated", "callee": "assertSame", "source_file": "C:\\Apache24\\htdocs\\ai\\vendor\\laravel\\breeze\\stubs\\inertia-common\\tests\\Feature\\ProfileTest.php", "source_location": "L41"}, {"caller_nid": "profiletest_profiletest_test_profile_information_can_be_updated", "callee": "assertSame", "source_file": "C:\\Apache24\\htdocs\\ai\\vendor\\laravel\\breeze\\stubs\\inertia-common\\tests\\Feature\\ProfileTest.php", "source_location": "L42"}, {"caller_nid": "profiletest_profiletest_test_profile_information_can_be_updated", "callee": "assertNull", "source_file": "C:\\Apache24\\htdocs\\ai\\vendor\\laravel\\breeze\\stubs\\inertia-common\\tests\\Feature\\ProfileTest.php", "source_location": "L43"}, {"caller_nid": "profiletest_profiletest_test_email_verification_status_is_unchanged_when_the_email_address_is_unchanged", "callee": "create", "source_file": "C:\\Apache24\\htdocs\\ai\\vendor\\laravel\\breeze\\stubs\\inertia-common\\tests\\Feature\\ProfileTest.php", "source_location": "L48"}, {"caller_nid": "profiletest_profiletest_test_email_verification_status_is_unchanged_when_the_email_address_is_unchanged", "callee": "User", "source_file": "C:\\Apache24\\htdocs\\ai\\vendor\\laravel\\breeze\\stubs\\inertia-common\\tests\\Feature\\ProfileTest.php", "source_location": "L48"}, {"caller_nid": "profiletest_profiletest_test_email_verification_status_is_unchanged_when_the_email_address_is_unchanged", "callee": "patch", "source_file": "C:\\Apache24\\htdocs\\ai\\vendor\\laravel\\breeze\\stubs\\inertia-common\\tests\\Feature\\ProfileTest.php", "source_location": "L50"}, {"caller_nid": "profiletest_profiletest_test_email_verification_status_is_unchanged_when_the_email_address_is_unchanged", "callee": "actingAs", "source_file": "C:\\Apache24\\htdocs\\ai\\vendor\\laravel\\breeze\\stubs\\inertia-common\\tests\\Feature\\ProfileTest.php", "source_location": "L50"}, {"caller_nid": "profiletest_profiletest_test_email_verification_status_is_unchanged_when_the_email_address_is_unchanged", "callee": "assertRedirect", "source_file": "C:\\Apache24\\htdocs\\ai\\vendor\\laravel\\breeze\\stubs\\inertia-common\\tests\\Feature\\ProfileTest.php", "source_location": "L57"}, {"caller_nid": "profiletest_profiletest_test_email_verification_status_is_unchanged_when_the_email_address_is_unchanged", "callee": "assertSessionHasNoErrors", "source_file": "C:\\Apache24\\htdocs\\ai\\vendor\\laravel\\breeze\\stubs\\inertia-common\\tests\\Feature\\ProfileTest.php", "source_location": "L57"}, {"caller_nid": "profiletest_profiletest_test_email_verification_status_is_unchanged_when_the_email_address_is_unchanged", "callee": "assertNotNull", "source_file": "C:\\Apache24\\htdocs\\ai\\vendor\\laravel\\breeze\\stubs\\inertia-common\\tests\\Feature\\ProfileTest.php", "source_location": "L61"}, {"caller_nid": "profiletest_profiletest_test_email_verification_status_is_unchanged_when_the_email_address_is_unchanged", "callee": "refresh", "source_file": "C:\\Apache24\\htdocs\\ai\\vendor\\laravel\\breeze\\stubs\\inertia-common\\tests\\Feature\\ProfileTest.php", "source_location": "L61"}, {"caller_nid": "profiletest_profiletest_test_user_can_delete_their_account", "callee": "create", "source_file": "C:\\Apache24\\htdocs\\ai\\vendor\\laravel\\breeze\\stubs\\inertia-common\\tests\\Feature\\ProfileTest.php", "source_location": "L66"}, {"caller_nid": "profiletest_profiletest_test_user_can_delete_their_account", "callee": "User", "source_file": "C:\\Apache24\\htdocs\\ai\\vendor\\laravel\\breeze\\stubs\\inertia-common\\tests\\Feature\\ProfileTest.php", "source_location": "L66"}, {"caller_nid": "profiletest_profiletest_test_user_can_delete_their_account", "callee": "delete", "source_file": "C:\\Apache24\\htdocs\\ai\\vendor\\laravel\\breeze\\stubs\\inertia-common\\tests\\Feature\\ProfileTest.php", "source_location": "L68"}, {"caller_nid": "profiletest_profiletest_test_user_can_delete_their_account", "callee": "actingAs", "source_file": "C:\\Apache24\\htdocs\\ai\\vendor\\laravel\\breeze\\stubs\\inertia-common\\tests\\Feature\\ProfileTest.php", "source_location": "L68"}, {"caller_nid": "profiletest_profiletest_test_user_can_delete_their_account", "callee": "assertRedirect", "source_file": "C:\\Apache24\\htdocs\\ai\\vendor\\laravel\\breeze\\stubs\\inertia-common\\tests\\Feature\\ProfileTest.php", "source_location": "L74"}, {"caller_nid": "profiletest_profiletest_test_user_can_delete_their_account", "callee": "assertSessionHasNoErrors", "source_file": "C:\\Apache24\\htdocs\\ai\\vendor\\laravel\\breeze\\stubs\\inertia-common\\tests\\Feature\\ProfileTest.php", "source_location": "L74"}, {"caller_nid": "profiletest_profiletest_test_user_can_delete_their_account", "callee": "assertGuest", "source_file": "C:\\Apache24\\htdocs\\ai\\vendor\\laravel\\breeze\\stubs\\inertia-common\\tests\\Feature\\ProfileTest.php", "source_location": "L78"}, {"caller_nid": "profiletest_profiletest_test_user_can_delete_their_account", "callee": "assertNull", "source_file": "C:\\Apache24\\htdocs\\ai\\vendor\\laravel\\breeze\\stubs\\inertia-common\\tests\\Feature\\ProfileTest.php", "source_location": "L79"}, {"caller_nid": "profiletest_profiletest_test_user_can_delete_their_account", "callee": "fresh", "source_file": "C:\\Apache24\\htdocs\\ai\\vendor\\laravel\\breeze\\stubs\\inertia-common\\tests\\Feature\\ProfileTest.php", "source_location": "L79"}, {"caller_nid": "profiletest_profiletest_test_correct_password_must_be_provided_to_delete_account", "callee": "create", "source_file": "C:\\Apache24\\htdocs\\ai\\vendor\\laravel\\breeze\\stubs\\inertia-common\\tests\\Feature\\ProfileTest.php", "source_location": "L84"}, {"caller_nid": "profiletest_profiletest_test_correct_password_must_be_provided_to_delete_account", "callee": "User", "source_file": "C:\\Apache24\\htdocs\\ai\\vendor\\laravel\\breeze\\stubs\\inertia-common\\tests\\Feature\\ProfileTest.php", "source_location": "L84"}, {"caller_nid": "profiletest_profiletest_test_correct_password_must_be_provided_to_delete_account", "callee": "delete", "source_file": "C:\\Apache24\\htdocs\\ai\\vendor\\laravel\\breeze\\stubs\\inertia-common\\tests\\Feature\\ProfileTest.php", "source_location": "L86"}, {"caller_nid": "profiletest_profiletest_test_correct_password_must_be_provided_to_delete_account", "callee": "from", "source_file": "C:\\Apache24\\htdocs\\ai\\vendor\\laravel\\breeze\\stubs\\inertia-common\\tests\\Feature\\ProfileTest.php", "source_location": "L86"}, {"caller_nid": "profiletest_profiletest_test_correct_password_must_be_provided_to_delete_account", "callee": "actingAs", "source_file": "C:\\Apache24\\htdocs\\ai\\vendor\\laravel\\breeze\\stubs\\inertia-common\\tests\\Feature\\ProfileTest.php", "source_location": "L86"}, {"caller_nid": "profiletest_profiletest_test_correct_password_must_be_provided_to_delete_account", "callee": "assertRedirect", "source_file": "C:\\Apache24\\htdocs\\ai\\vendor\\laravel\\breeze\\stubs\\inertia-common\\tests\\Feature\\ProfileTest.php", "source_location": "L93"}, {"caller_nid": "profiletest_profiletest_test_correct_password_must_be_provided_to_delete_account", "callee": "assertSessionHasErrors", "source_file": "C:\\Apache24\\htdocs\\ai\\vendor\\laravel\\breeze\\stubs\\inertia-common\\tests\\Feature\\ProfileTest.php", "source_location": "L93"}, {"caller_nid": "profiletest_profiletest_test_correct_password_must_be_provided_to_delete_account", "callee": "assertNotNull", "source_file": "C:\\Apache24\\htdocs\\ai\\vendor\\laravel\\breeze\\stubs\\inertia-common\\tests\\Feature\\ProfileTest.php", "source_location": "L97"}, {"caller_nid": "profiletest_profiletest_test_correct_password_must_be_provided_to_delete_account", "callee": "fresh", "source_file": "C:\\Apache24\\htdocs\\ai\\vendor\\laravel\\breeze\\stubs\\inertia-common\\tests\\Feature\\ProfileTest.php", "source_location": "L97"}]}