{"nodes": [{"id": "c_apache24_htdocs_ai_app_http_controllers_client_invoicecontroller_php", "label": "InvoiceController.php", "file_type": "code", "source_file": "C:\\Apache24\\htdocs\\ai\\app\\Http\\Controllers\\Client\\InvoiceController.php", "source_location": "L1"}, {"id": "invoicecontroller_invoicecontroller", "label": "InvoiceController", "file_type": "code", "source_file": "C:\\Apache24\\htdocs\\ai\\app\\Http\\Controllers\\Client\\InvoiceController.php", "source_location": "L11"}, {"id": "invoicecontroller_invoicecontroller_index", "label": ".index()", "file_type": "code", "source_file": "C:\\Apache24\\htdocs\\ai\\app\\Http\\Controllers\\Client\\InvoiceController.php", "source_location": "L13"}, {"id": "invoicecontroller_invoicecontroller_pay", "label": ".pay()", "file_type": "code", "source_file": "C:\\Apache24\\htdocs\\ai\\app\\Http\\Controllers\\Client\\InvoiceController.php", "source_location": "L28"}, {"id": "invoicecontroller_invoicecontroller_paywithesewa", "label": ".payWithESewa()", "file_type": "code", "source_file": "C:\\Apache24\\htdocs\\ai\\app\\Http\\Controllers\\Client\\InvoiceController.php", "source_location": "L51"}, {"id": "invoicecontroller_invoicecontroller_paywithkhalti", "label": ".payWithKhalti()", "file_type": "code", "source_file": "C:\\Apache24\\htdocs\\ai\\app\\Http\\Controllers\\Client\\InvoiceController.php", "source_location": "L89"}, {"id": "invoicecontroller_invoicecontroller_callback", "label": ".callback()", "file_type": "code", "source_file": "C:\\Apache24\\htdocs\\ai\\app\\Http\\Controllers\\Client\\InvoiceController.php", "source_location": "L127"}], "edges": [{"source": "c_apache24_htdocs_ai_app_http_controllers_client_invoicecontroller_php", "target": "controller", "relation": "imports", "confidence": "EXTRACTED", "source_file": "C:\\Apache24\\htdocs\\ai\\app\\Http\\Controllers\\Client\\InvoiceController.php", "source_location": "L5", "weight": 1.0}, {"source": "c_apache24_htdocs_ai_app_http_controllers_client_invoicecontroller_php", "target": "invoice", "relation": "imports", "confidence": "EXTRACTED", "source_file": "C:\\Apache24\\htdocs\\ai\\app\\Http\\Controllers\\Client\\InvoiceController.php", "source_location": "L6", "weight": 1.0}, {"source": "c_apache24_htdocs_ai_app_http_controllers_client_invoicecontroller_php", "target": "redirectresponse", "relation": "imports", "confidence": "EXTRACTED", "source_file": "C:\\Apache24\\htdocs\\ai\\app\\Http\\Controllers\\Client\\InvoiceController.php", "source_location": "L7", "weight": 1.0}, {"source": "c_apache24_htdocs_ai_app_http_controllers_client_invoicecontroller_php", "target": "request", "relation": "imports", "confidence": "EXTRACTED", "source_file": "C:\\Apache24\\htdocs\\ai\\app\\Http\\Controllers\\Client\\InvoiceController.php", "source_location": "L8", "weight": 1.0}, {"source": "c_apache24_htdocs_ai_app_http_controllers_client_invoicecontroller_php", "target": "view", "relation": "imports", "confidence": "EXTRACTED", "source_file": "C:\\Apache24\\htdocs\\ai\\app\\Http\\Controllers\\Client\\InvoiceController.php", "source_location": "L9", "weight": 1.0}, {"source": "c_apache24_htdocs_ai_app_http_controllers_client_invoicecontroller_php", "target": "invoicecontroller_invoicecontroller", "relation": "contains", "confidence": "EXTRACTED", "source_file": "C:\\Apache24\\htdocs\\ai\\app\\Http\\Controllers\\Client\\InvoiceController.php", "source_location": "L11", "weight": 1.0}, {"source": "invoicecontroller_invoicecontroller", "target": "invoicecontroller_invoicecontroller_index", "relation": "method", "confidence": "EXTRACTED", "source_file": "C:\\Apache24\\htdocs\\ai\\app\\Http\\Controllers\\Client\\InvoiceController.php", "source_location": "L13", "weight": 1.0}, {"source": "invoicecontroller_invoicecontroller", "target": "invoicecontroller_invoicecontroller_pay", "relation": "method", "confidence": "EXTRACTED", "source_file": "C:\\Apache24\\htdocs\\ai\\app\\Http\\Controllers\\Client\\InvoiceController.php", "source_location": "L28", "weight": 1.0}, {"source": "invoicecontroller_invoicecontroller", "target": "invoicecontroller_invoicecontroller_paywithesewa", "relation": "method", "confidence": "EXTRACTED", "source_file": "C:\\Apache24\\htdocs\\ai\\app\\Http\\Controllers\\Client\\InvoiceController.php", "source_location": "L51", "weight": 1.0}, {"source": "invoicecontroller_invoicecontroller", "target": "invoicecontroller_invoicecontroller_paywithkhalti", "relation": "method", "confidence": "EXTRACTED", "source_file": "C:\\Apache24\\htdocs\\ai\\app\\Http\\Controllers\\Client\\InvoiceController.php", "source_location": "L89", "weight": 1.0}, {"source": "invoicecontroller_invoicecontroller", "target": "invoicecontroller_invoicecontroller_callback", "relation": "method", "confidence": "EXTRACTED", "source_file": "C:\\Apache24\\htdocs\\ai\\app\\Http\\Controllers\\Client\\InvoiceController.php", "source_location": "L127", "weight": 1.0}, {"source": "invoicecontroller_invoicecontroller_pay", "target": "invoicecontroller_invoicecontroller_paywithesewa", "relation": "calls", "confidence": "EXTRACTED", "source_file": "C:\\Apache24\\htdocs\\ai\\app\\Http\\Controllers\\Client\\InvoiceController.php", "source_location": "L43", "weight": 1.0}, {"source": "invoicecontroller_invoicecontroller_pay", "target": "invoicecontroller_invoicecontroller_paywithkhalti", "relation": "calls", "confidence": "EXTRACTED", "source_file": "C:\\Apache24\\htdocs\\ai\\app\\Http\\Controllers\\Client\\InvoiceController.php", "source_location": "L45", "weight": 1.0}], "raw_calls": [{"caller_nid": "invoicecontroller_invoicecontroller_index", "callee": "user", "source_file": "C:\\Apache24\\htdocs\\ai\\app\\Http\\Controllers\\Client\\InvoiceController.php", "source_location": "L15"}, {"caller_nid": "invoicecontroller_invoicecontroller_index", "callee": "auth", "source_file": "C:\\Apache24\\htdocs\\ai\\app\\Http\\Controllers\\Client\\InvoiceController.php", "source_location": "L15"}, {"caller_nid": "invoicecontroller_invoicecontroller_index", "callee": "paginate", "source_file": "C:\\Apache24\\htdocs\\ai\\app\\Http\\Controllers\\Client\\InvoiceController.php", "source_location": "L17"}, {"caller_nid": "invoicecontroller_invoicecontroller_index", "callee": "orderBy", "source_file": "C:\\Apache24\\htdocs\\ai\\app\\Http\\Controllers\\Client\\InvoiceController.php", "source_location": "L17"}, {"caller_nid": "invoicecontroller_invoicecontroller_index", "callee": "invoices", "source_file": "C:\\Apache24\\htdocs\\ai\\app\\Http\\Controllers\\Client\\InvoiceController.php", "source_location": "L17"}, {"caller_nid": "invoicecontroller_invoicecontroller_index", "callee": "sum", "source_file": "C:\\Apache24\\htdocs\\ai\\app\\Http\\Controllers\\Client\\InvoiceController.php", "source_location": "L21"}, {"caller_nid": "invoicecontroller_invoicecontroller_index", "callee": "where", "source_file": "C:\\Apache24\\htdocs\\ai\\app\\Http\\Controllers\\Client\\InvoiceController.php", "source_location": "L21"}, {"caller_nid": "invoicecontroller_invoicecontroller_index", "callee": "invoices", "source_file": "C:\\Apache24\\htdocs\\ai\\app\\Http\\Controllers\\Client\\InvoiceController.php", "source_location": "L21"}, {"caller_nid": "invoicecontroller_invoicecontroller_index", "callee": "view", "source_file": "C:\\Apache24\\htdocs\\ai\\app\\Http\\Controllers\\Client\\InvoiceController.php", "source_location": "L25"}, {"caller_nid": "invoicecontroller_invoicecontroller_index", "callee": "compact", "source_file": "C:\\Apache24\\htdocs\\ai\\app\\Http\\Controllers\\Client\\InvoiceController.php", "source_location": "L25"}, {"caller_nid": "invoicecontroller_invoicecontroller_pay", "callee": "user", "source_file": "C:\\Apache24\\htdocs\\ai\\app\\Http\\Controllers\\Client\\InvoiceController.php", "source_location": "L30"}, {"caller_nid": "invoicecontroller_invoicecontroller_pay", "callee": "auth", "source_file": "C:\\Apache24\\htdocs\\ai\\app\\Http\\Controllers\\Client\\InvoiceController.php", "source_location": "L30"}, {"caller_nid": "invoicecontroller_invoicecontroller_pay", "callee": "abort", "source_file": "C:\\Apache24\\htdocs\\ai\\app\\Http\\Controllers\\Client\\InvoiceController.php", "source_location": "L33"}, {"caller_nid": "invoicecontroller_invoicecontroller_pay", "callee": "isPaid", "source_file": "C:\\Apache24\\htdocs\\ai\\app\\Http\\Controllers\\Client\\InvoiceController.php", "source_location": "L36"}, {"caller_nid": "invoicecontroller_invoicecontroller_pay", "callee": "with", "source_file": "C:\\Apache24\\htdocs\\ai\\app\\Http\\Controllers\\Client\\InvoiceController.php", "source_location": "L37"}, {"caller_nid": "invoicecontroller_invoicecontroller_pay", "callee": "back", "source_file": "C:\\Apache24\\htdocs\\ai\\app\\Http\\Controllers\\Client\\InvoiceController.php", "source_location": "L37"}, {"caller_nid": "invoicecontroller_invoicecontroller_pay", "callee": "redirect", "source_file": "C:\\Apache24\\htdocs\\ai\\app\\Http\\Controllers\\Client\\InvoiceController.php", "source_location": "L37"}, {"caller_nid": "invoicecontroller_invoicecontroller_pay", "callee": "request", "source_file": "C:\\Apache24\\htdocs\\ai\\app\\Http\\Controllers\\Client\\InvoiceController.php", "source_location": "L40"}, {"caller_nid": "invoicecontroller_invoicecontroller_pay", "callee": "with", "source_file": "C:\\Apache24\\htdocs\\ai\\app\\Http\\Controllers\\Client\\InvoiceController.php", "source_location": "L48"}, {"caller_nid": "invoicecontroller_invoicecontroller_pay", "callee": "back", "source_file": "C:\\Apache24\\htdocs\\ai\\app\\Http\\Controllers\\Client\\InvoiceController.php", "source_location": "L48"}, {"caller_nid": "invoicecontroller_invoicecontroller_pay", "callee": "redirect", "source_file": "C:\\Apache24\\htdocs\\ai\\app\\Http\\Controllers\\Client\\InvoiceController.php", "source_location": "L48"}, {"caller_nid": "invoicecontroller_invoicecontroller_paywithesewa", "callee": "config", "source_file": "C:\\Apache24\\htdocs\\ai\\app\\Http\\Controllers\\Client\\InvoiceController.php", "source_location": "L53"}, {"caller_nid": "invoicecontroller_invoicecontroller_paywithesewa", "callee": "env", "source_file": "C:\\Apache24\\htdocs\\ai\\app\\Http\\Controllers\\Client\\InvoiceController.php", "source_location": "L53"}, {"caller_nid": "invoicecontroller_invoicecontroller_paywithesewa", "callee": "url", "source_file": "C:\\Apache24\\htdocs\\ai\\app\\Http\\Controllers\\Client\\InvoiceController.php", "source_location": "L65"}, {"caller_nid": "invoicecontroller_invoicecontroller_paywithesewa", "callee": "url", "source_file": "C:\\Apache24\\htdocs\\ai\\app\\Http\\Controllers\\Client\\InvoiceController.php", "source_location": "L66"}, {"caller_nid": "invoicecontroller_invoicecontroller_paywithesewa", "callee": "base64_encode", "source_file": "C:\\Apache24\\htdocs\\ai\\app\\Http\\Controllers\\Client\\InvoiceController.php", "source_location": "L69"}, {"caller_nid": "invoicecontroller_invoicecontroller_paywithesewa", "callee": "json_encode", "source_file": "C:\\Apache24\\htdocs\\ai\\app\\Http\\Controllers\\Client\\InvoiceController.php", "source_location": "L69"}, {"caller_nid": "invoicecontroller_invoicecontroller_paywithesewa", "callee": "hash_hmac", "source_file": "C:\\Apache24\\htdocs\\ai\\app\\Http\\Controllers\\Client\\InvoiceController.php", "source_location": "L70"}, {"caller_nid": "invoicecontroller_invoicecontroller_paywithesewa", "callee": "config", "source_file": "C:\\Apache24\\htdocs\\ai\\app\\Http\\Controllers\\Client\\InvoiceController.php", "source_location": "L70"}, {"caller_nid": "invoicecontroller_invoicecontroller_paywithesewa", "callee": "base64_encode", "source_file": "C:\\Apache24\\htdocs\\ai\\app\\Http\\Controllers\\Client\\InvoiceController.php", "source_location": "L71"}, {"caller_nid": "invoicecontroller_invoicecontroller_paywithesewa", "callee": "config", "source_file": "C:\\Apache24\\htdocs\\ai\\app\\Http\\Controllers\\Client\\InvoiceController.php", "source_location": "L73"}, {"caller_nid": "invoicecontroller_invoicecontroller_paywithesewa", "callee": "redirect", "source_file": "C:\\Apache24\\htdocs\\ai\\app\\Http\\Controllers\\Client\\InvoiceController.php", "source_location": "L77"}, {"caller_nid": "invoicecontroller_invoicecontroller_paywithesewa", "callee": "http_build_query", "source_file": "C:\\Apache24\\htdocs\\ai\\app\\Http\\Controllers\\Client\\InvoiceController.php", "source_location": "L77"}, {"caller_nid": "invoicecontroller_invoicecontroller_paywithkhalti", "callee": "config", "source_file": "C:\\Apache24\\htdocs\\ai\\app\\Http\\Controllers\\Client\\InvoiceController.php", "source_location": "L91"}, {"caller_nid": "invoicecontroller_invoicecontroller_paywithkhalti", "callee": "env", "source_file": "C:\\Apache24\\htdocs\\ai\\app\\Http\\Controllers\\Client\\InvoiceController.php", "source_location": "L91"}, {"caller_nid": "invoicecontroller_invoicecontroller_paywithkhalti", "callee": "url", "source_file": "C:\\Apache24\\htdocs\\ai\\app\\Http\\Controllers\\Client\\InvoiceController.php", "source_location": "L95"}, {"caller_nid": "invoicecontroller_invoicecontroller_paywithkhalti", "callee": "url", "source_file": "C:\\Apache24\\htdocs\\ai\\app\\Http\\Controllers\\Client\\InvoiceController.php", "source_location": "L96"}, {"caller_nid": "invoicecontroller_invoicecontroller_paywithkhalti", "callee": "user", "source_file": "C:\\Apache24\\htdocs\\ai\\app\\Http\\Controllers\\Client\\InvoiceController.php", "source_location": "L100"}, {"caller_nid": "invoicecontroller_invoicecontroller_paywithkhalti", "callee": "auth", "source_file": "C:\\Apache24\\htdocs\\ai\\app\\Http\\Controllers\\Client\\InvoiceController.php", "source_location": "L100"}, {"caller_nid": "invoicecontroller_invoicecontroller_paywithkhalti", "callee": "user", "source_file": "C:\\Apache24\\htdocs\\ai\\app\\Http\\Controllers\\Client\\InvoiceController.php", "source_location": "L101"}, {"caller_nid": "invoicecontroller_invoicecontroller_paywithkhalti", "callee": "auth", "source_file": "C:\\Apache24\\htdocs\\ai\\app\\Http\\Controllers\\Client\\InvoiceController.php", "source_location": "L101"}, {"caller_nid": "invoicecontroller_invoicecontroller_paywithkhalti", "callee": "curl_init", "source_file": "C:\\Apache24\\htdocs\\ai\\app\\Http\\Controllers\\Client\\InvoiceController.php", "source_location": "L105"}, {"caller_nid": "invoicecontroller_invoicecontroller_paywithkhalti", "callee": "curl_setopt", "source_file": "C:\\Apache24\\htdocs\\ai\\app\\Http\\Controllers\\Client\\InvoiceController.php", "source_location": "L106"}, {"caller_nid": "invoicecontroller_invoicecontroller_paywithkhalti", "callee": "curl_setopt", "source_file": "C:\\Apache24\\htdocs\\ai\\app\\Http\\Controllers\\Client\\InvoiceController.php", "source_location": "L107"}, {"caller_nid": "invoicecontroller_invoicecontroller_paywithkhalti", "callee": "curl_setopt", "source_file": "C:\\Apache24\\htdocs\\ai\\app\\Http\\Controllers\\Client\\InvoiceController.php", "source_location": "L108"}, {"caller_nid": "invoicecontroller_invoicecontroller_paywithkhalti", "callee": "json_encode", "source_file": "C:\\Apache24\\htdocs\\ai\\app\\Http\\Controllers\\Client\\InvoiceController.php", "source_location": "L108"}, {"caller_nid": "invoicecontroller_invoicecontroller_paywithkhalti", "callee": "curl_setopt", "source_file": "C:\\Apache24\\htdocs\\ai\\app\\Http\\Controllers\\Client\\InvoiceController.php", "source_location": "L109"}, {"caller_nid": "invoicecontroller_invoicecontroller_paywithkhalti", "callee": "curl_setopt", "source_file": "C:\\Apache24\\htdocs\\ai\\app\\Http\\Controllers\\Client\\InvoiceController.php", "source_location": "L110"}, {"caller_nid": "invoicecontroller_invoicecontroller_paywithkhalti", "callee": "curl_exec", "source_file": "C:\\Apache24\\htdocs\\ai\\app\\Http\\Controllers\\Client\\InvoiceController.php", "source_location": "L115"}, {"caller_nid": "invoicecontroller_invoicecontroller_paywithkhalti", "callee": "curl_close", "source_file": "C:\\Apache24\\htdocs\\ai\\app\\Http\\Controllers\\Client\\InvoiceController.php", "source_location": "L116"}, {"caller_nid": "invoicecontroller_invoicecontroller_paywithkhalti", "callee": "json_decode", "source_file": "C:\\Apache24\\htdocs\\ai\\app\\Http\\Controllers\\Client\\InvoiceController.php", "source_location": "L118"}, {"caller_nid": "invoicecontroller_invoicecontroller_paywithkhalti", "callee": "isset", "source_file": "C:\\Apache24\\htdocs\\ai\\app\\Http\\Controllers\\Client\\InvoiceController.php", "source_location": "L120"}, {"caller_nid": "invoicecontroller_invoicecontroller_paywithkhalti", "callee": "redirect", "source_file": "C:\\Apache24\\htdocs\\ai\\app\\Http\\Controllers\\Client\\InvoiceController.php", "source_location": "L121"}, {"caller_nid": "invoicecontroller_invoicecontroller_paywithkhalti", "callee": "with", "source_file": "C:\\Apache24\\htdocs\\ai\\app\\Http\\Controllers\\Client\\InvoiceController.php", "source_location": "L124"}, {"caller_nid": "invoicecontroller_invoicecontroller_paywithkhalti", "callee": "back", "source_file": "C:\\Apache24\\htdocs\\ai\\app\\Http\\Controllers\\Client\\InvoiceController.php", "source_location": "L124"}, {"caller_nid": "invoicecontroller_invoicecontroller_paywithkhalti", "callee": "redirect", "source_file": "C:\\Apache24\\htdocs\\ai\\app\\Http\\Controllers\\Client\\InvoiceController.php", "source_location": "L124"}, {"caller_nid": "invoicecontroller_invoicecontroller_callback", "callee": "markAsPaid", "source_file": "C:\\Apache24\\htdocs\\ai\\app\\Http\\Controllers\\Client\\InvoiceController.php", "source_location": "L130"}, {"caller_nid": "invoicecontroller_invoicecontroller_callback", "callee": "with", "source_file": "C:\\Apache24\\htdocs\\ai\\app\\Http\\Controllers\\Client\\InvoiceController.php", "source_location": "L132"}, {"caller_nid": "invoicecontroller_invoicecontroller_callback", "callee": "route", "source_file": "C:\\Apache24\\htdocs\\ai\\app\\Http\\Controllers\\Client\\InvoiceController.php", "source_location": "L132"}, {"caller_nid": "invoicecontroller_invoicecontroller_callback", "callee": "redirect", "source_file": "C:\\Apache24\\htdocs\\ai\\app\\Http\\Controllers\\Client\\InvoiceController.php", "source_location": "L132"}, {"caller_nid": "invoicecontroller_invoicecontroller_callback", "callee": "with", "source_file": "C:\\Apache24\\htdocs\\ai\\app\\Http\\Controllers\\Client\\InvoiceController.php", "source_location": "L136"}, {"caller_nid": "invoicecontroller_invoicecontroller_callback", "callee": "route", "source_file": "C:\\Apache24\\htdocs\\ai\\app\\Http\\Controllers\\Client\\InvoiceController.php", "source_location": "L136"}, {"caller_nid": "invoicecontroller_invoicecontroller_callback", "callee": "redirect", "source_file": "C:\\Apache24\\htdocs\\ai\\app\\Http\\Controllers\\Client\\InvoiceController.php", "source_location": "L136"}]}