{"nodes": [{"id": "c_apache24_htdocs_ai_vendor_laravel_breeze_stubs_api_routes_auth_php", "label": "auth.php", "file_type": "code", "source_file": "C:\\Apache24\\htdocs\\ai\\vendor\\laravel\\breeze\\stubs\\api\\routes\\auth.php", "source_location": "L1"}], "edges": [{"source": "c_apache24_htdocs_ai_vendor_laravel_breeze_stubs_api_routes_auth_php", "target": "authenticatedsessioncontroller", "relation": "imports", "confidence": "EXTRACTED", "source_file": "C:\\Apache24\\htdocs\\ai\\vendor\\laravel\\breeze\\stubs\\api\\routes\\auth.php", "source_location": "L3", "weight": 1.0}, {"source": "c_apache24_htdocs_ai_vendor_laravel_breeze_stubs_api_routes_auth_php", "target": "emailverificationnotificationcontroller", "relation": "imports", "confidence": "EXTRACTED", "source_file": "C:\\Apache24\\htdocs\\ai\\vendor\\laravel\\breeze\\stubs\\api\\routes\\auth.php", "source_location": "L4", "weight": 1.0}, {"source": "c_apache24_htdocs_ai_vendor_laravel_breeze_stubs_api_routes_auth_php", "target": "newpasswordcontroller", "relation": "imports", "confidence": "EXTRACTED", "source_file": "C:\\Apache24\\htdocs\\ai\\vendor\\laravel\\breeze\\stubs\\api\\routes\\auth.php", "source_location": "L5", "weight": 1.0}, {"source": "c_apache24_htdocs_ai_vendor_laravel_breeze_stubs_api_routes_auth_php", "target": "passwordresetlinkcontroller", "relation": "imports", "confidence": "EXTRACTED", "source_file": "C:\\Apache24\\htdocs\\ai\\vendor\\laravel\\breeze\\stubs\\api\\routes\\auth.php", "source_location": "L6", "weight": 1.0}, {"source": "c_apache24_htdocs_ai_vendor_laravel_breeze_stubs_api_routes_auth_php", "target": "registeredusercontroller", "relation": "imports", "confidence": "EXTRACTED", "source_file": "C:\\Apache24\\htdocs\\ai\\vendor\\laravel\\breeze\\stubs\\api\\routes\\auth.php", "source_location": "L7", "weight": 1.0}, {"source": "c_apache24_htdocs_ai_vendor_laravel_breeze_stubs_api_routes_auth_php", "target": "verifyemailcontroller", "relation": "imports", "confidence": "EXTRACTED", "source_file": "C:\\Apache24\\htdocs\\ai\\vendor\\laravel\\breeze\\stubs\\api\\routes\\auth.php", "source_location": "L8", "weight": 1.0}, {"source": "c_apache24_htdocs_ai_vendor_laravel_breeze_stubs_api_routes_auth_php", "target": "route", "relation": "imports", "confidence": "EXTRACTED", "source_file": "C:\\Apache24\\htdocs\\ai\\vendor\\laravel\\breeze\\stubs\\api\\routes\\auth.php", "source_location": "L9", "weight": 1.0}], "raw_calls": []}